ntp_time/__init__.py
ntp_time/test.py
ntp_time-0.0.0.dist-info/METADATA
ntp_time-0.0.0.dist-info/WHEEL
ntp_time-0.0.0.dist-info/top_level.txt
ntp_time-0.0.0.dist-info/RECORD
